[
    {
        "Level": "5",
        "Name": "5 TULIP"
    },
    {
        "Level": "4",
        "Name": "HIBISCUS"
    },
    {
        "Level": "3",
        "Name": "3 NILAM"
    },
    {
        "Level": "3",
        "Name": "ORKID"
    },
    {
        "Level": "1",
        "Name": "1 HIBISCUS"
    },
    {
        "Level": "2",
        "Name": "NILAM"
    },
    {
        "Level": "1",
        "Name": "HIBISCUS"
    },
    {
        "Level": "3",
        "Name": "3 DAHLIA"
    },
    {
        "Level": "3",
        "Name": "3 ORKID"
    },
    {
        "Level": "1",
        "Name": "LAVENDER"
    },
    {
        "Level": "3",
        "Name": "3 RAFLESIA"
    },
    {
        "Level": "5",
        "Name": "5 LAVENDER"
    },
    {
        "Level": "2",
        "Name": "2 LAVENDER"
    },
    {
        "Level": "5",
        "Name": "HIBISCUS"
    },
    {
        "Level": "3",
        "Name": "3 HIBISCUS"
    },
    {
        "Level": "4",
        "Name": "BERLIAN"
    },
    {
        "Level": "1",
        "Name": "1 TULIP"
    },
    {
        "Level": "1",
        "Name": "1 DAHLIA"
    },
    {
        "Level": "4",
        "Name": "4 DAHLIA"
    },
    {
        "Level": "4",
        "Name": "4 HIBISCUS"
    },
    {
        "Level": "P",
        "Name": "2"
    },
    {
        "Level": "3",
        "Name": "DAHLIA"
    },
    {
        "Level": "4",
        "Name": "4 BERLIAN"
    },
    {
        "Level": "5",
        "Name": "LAVENDER"
    },
    {
        "Level": "4",
        "Name": "IXORA"
    },
    {
        "Level": "1",
        "Name": "IXORA"
    },
    {
        "Level": "3",
        "Name": "3 AKASIA"
    },
    {
        "Level": "2",
        "Name": "HIBISCUS"
    },
    {
        "Level": "3",
        "Name": "AKASIA"
    },
    {
        "Level": "2",
        "Name": "2 RAFLESIA"
    },
    {
        "Level": "1",
        "Name": "NILAM"
    },
    {
        "Level": "5",
        "Name": "5 ORKID"
    },
    {
        "Level": "3",
        "Name": "3 BERLIAN 2025"
    },
    {
        "Level": "3",
        "Name": "LAVENDER"
    },
    {
        "Level": "5",
        "Name": "NILAM"
    },
    {
        "Level": "3",
        "Name": "ZAMRUD"
    },
    {
        "Level": "2",
        "Name": "BERLIAN"
    },
    {
        "Level": "2",
        "Name": "IXORA"
    },
    {
        "Level": "4",
        "Name": "RAFLESIA"
    },
    {
        "Level": "3",
        "Name": "NILAM"
    },
    {
        "Level": "1",
        "Name": "ALUMNI"
    },
    {
        "Level": "2",
        "Name": "2 ZAMRUD"
    },
    {
        "Level": "5",
        "Name": "5 RAFLESIA"
    },
    {
        "Level": "5",
        "Name": "5 NILAM"
    },
    {
        "Level": "1",
        "Name": "BERLIAN"
    },
    {
        "Level": "2",
        "Name": "2 ORKID"
    },
    {
        "Level": "2",
        "Name": "RAFLESIA"
    },
    {
        "Level": "5",
        "Name": "BERLIAN"
    },
    {
        "Level": "3",
        "Name": "HIBISCUS"
    },
    {
        "Level": "4",
        "Name": "TULIP"
    },
    {
        "Level": "4",
        "Name": "4 LAVENDER"
    },
    {
        "Level": "1",
        "Name": "1 AKASIA"
    },
    {
        "Level": "3",
        "Name": "BERLIAN"
    },
    {
        "Level": "5",
        "Name": "5 IXORA"
    },
    {
        "Level": "4",
        "Name": "4 ORKID"
    },
    {
        "Level": "3",
        "Name": "IXORA"
    },
    {
        "Level": "1",
        "Name": "1 ORKID"
    },
    {
        "Level": "1",
        "Name": "RAFLESIA"
    },
    {
        "Level": "4",
        "Name": "4 AKASIA"
    },
    {
        "Level": "4",
        "Name": "4 IXORA"
    },
    {
        "Level": "3",
        "Name": "3 TULIP"
    },
    {
        "Level": "5",
        "Name": "RAFLESIA"
    },
    {
        "Level": "4",
        "Name": "4 RAFLESIA"
    },
    {
        "Level": "2",
        "Name": "TULIP"
    },
    {
        "Level": "1",
        "Name": "1 ZAMRUD"
    },
    {
        "Level": "2",
        "Name": "2 BERLIAN"
    },
    {
        "Level": "3",
        "Name": "3 BERLIAN"
    },
    {
        "Level": "1",
        "Name": "1 RAFLESIA"
    },
    {
        "Level": "PERALIHAN",
        "Name": "PERALIHAN"
    },
    {
        "Level": "1",
        "Name": "1 BERLIAN"
    },
    {
        "Level": "4",
        "Name": "DAHLIA"
    },
    {
        "Level": "5",
        "Name": "5 ZAMRUD"
    },
    {
        "Level": "1",
        "Name": "DAHLIA"
    },
    {
        "Level": "3",
        "Name": "RAFLESIA"
    },
    {
        "Level": "2",
        "Name": "2 NILAM"
    },
    {
        "Level": "3",
        "Name": "3 IXORA"
    },
    {
        "Level": "3",
        "Name": "3 LAVENDER"
    },
    {
        "Level": "2",
        "Name": "ORKID"
    },
    {
        "Level": "4",
        "Name": "AKASIA"
    },
    {
        "Level": "1",
        "Name": "AKASIA"
    },
    {
        "Level": "5",
        "Name": "DAHLIA"
    },
    {
        "Level": "1",
        "Name": "TULIP"
    },
    {
        "Level": "4",
        "Name": "LAVENDER"
    },
    {
        "Level": "1",
        "Name": "1 NILAM"
    },
    {
        "Level": "2",
        "Name": "2 IXORA"
    },
    {
        "Level": "4",
        "Name": "ZAMRUD"
    },
    {
        "Level": "2",
        "Name": "2 AKASIA"
    },
    {
        "Level": "5",
        "Name": "AKASIA"
    },
    {
        "Level": "5",
        "Name": "TULIP"
    },
    {
        "Level": "1",
        "Name": "ZAMRUD"
    },
    {
        "Level": "4",
        "Name": "4 ZAMRUD"
    },
    {
        "Level": "2",
        "Name": "DAHLIA"
    },
    {
        "Level": "4",
        "Name": "ORKID"
    },
    {
        "Level": "5",
        "Name": "5 AKASIA"
    },
    {
        "Level": "1",
        "Name": "ORKID"
    },
    {
        "Level": "5",
        "Name": "ZAMRUD"
    },
    {
        "Level": "1",
        "Name": "1 IXORA"
    },
    {
        "Level": "4",
        "Name": "NILAM"
    },
    {
        "Level": "2",
        "Name": "AKASIA"
    },
    {
        "Level": "KELAS",
        "Name": "ALUMNI"
    },
    {
        "Level": "2",
        "Name": "2 TULIP"
    },
    {
        "Level": "3",
        "Name": "TULIP"
    },
    {
        "Level": "3",
        "Name": "3 ZAMRUD"
    },
    {
        "Level": "5",
        "Name": "5 DAHLIA"
    },
    {
        "Level": "2",
        "Name": "2 DAHLIA"
    },
    {
        "Level": "4",
        "Name": "4 NILAM"
    },
    {
        "Level": "5",
        "Name": "ORKID"
    },
    {
        "Level": "2",
        "Name": "LAVENDER"
    },
    {
        "Level": "PERALIHAN",
        "Name": "P1"
    },
    {
        "Level": "5",
        "Name": "5 HIBISCUS"
    },
    {
        "Level": "4",
        "Name": "4 TULIP"
    },
    {
        "Level": "2",
        "Name": "2 HIBISCUS"
    },
    {
        "Level": "2",
        "Name": "ZAMRUD"
    },
    {
        "Level": "5",
        "Name": "5 BERLIAN"
    },
    {
        "Level": "1",
        "Name": "1 LAVENDER"
    }
]