[
    {
        "Level": "4",
        "Name": "RC2"
    },
    {
        "Level": "5",
        "Name": "P2"
    },
    {
        "Level": "2",
        "Name": "UMS"
    },
    {
        "Level": "5",
        "Name": "RC"
    },
    {
        "Level": "5",
        "Name": "SAINS"
    },
    {
        "Level": "2",
        "Name": "UPSI"
    },
    {
        "Level": "5",
        "Name": "K3"
    },
    {
        "Level": "2",
        "Name": "UNIMAS"
    },
    {
        "Level": "PER",
        "Name": "A"
    },
    {
        "Level": "5",
        "Name": "K5"
    },
    {
        "Level": "1",
        "Name": "UPSI"
    },
    {
        "Level": "1",
        "Name": "1UTM"
    },
    {
        "Level": "1",
        "Name": "UKM"
    },
    {
        "Level": "2",
        "Name": "UM"
    },
    {
        "Level": "4",
        "Name": "K4"
    },
    {
        "Level": "3",
        "Name": "UMS"
    },
    {
        "Level": "1",
        "Name": "1UUM"
    },
    {
        "Level": "3",
        "Name": "UPSI"
    },
    {
        "Level": "1",
        "Name": "ALUMNI"
    },
    {
        "Level": "2",
        "Name": "UUM"
    },
    {
        "Level": "3",
        "Name": "UNIMAS"
    },
    {
        "Level": "4",
        "Name": "P1"
    },
    {
        "Level": "1",
        "Name": "1USM"
    },
    {
        "Level": "2",
        "Name": "UKM"
    },
    {
        "Level": "2",
        "Name": "UMP"
    },
    {
        "Level": "1",
        "Name": "UM"
    },
    {
        "Level": "4",
        "Name": "K1"
    },
    {
        "Level": "1",
        "Name": "USM"
    },
    {
        "Level": "2",
        "Name": "UTM"
    },
    {
        "Level": "1",
        "Name": "UPM"
    },
    {
        "Level": "1",
        "Name": "UUM"
    },
    {
        "Level": "1",
        "Name": "UITM"
    },
    {
        "Level": "2",
        "Name": "UIA"
    },
    {
        "Level": "4",
        "Name": "2"
    },
    {
        "Level": "1",
        "Name": "UMP"
    },
    {
        "Level": "3",
        "Name": "UM"
    },
    {
        "Level": "2",
        "Name": "USM"
    },
    {
        "Level": "PER",
        "Name": "B"
    },
    {
        "Level": "1",
        "Name": "UTM"
    },
    {
        "Level": "4",
        "Name": "P"
    },
    {
        "Level": "2",
        "Name": "UPM"
    },
    {
        "Level": "2",
        "Name": "UITM"
    },
    {
        "Level": "5",
        "Name": "K4"
    },
    {
        "Level": "1",
        "Name": "1UMS"
    },
    {
        "Level": "3",
        "Name": "UUM"
    },
    {
        "Level": "5",
        "Name": "5K3"
    },
    {
        "Level": "1",
        "Name": "UIA"
    },
    {
        "Level": "1",
        "Name": "1UPSI"
    },
    {
        "Level": "3",
        "Name": "UKM"
    },
    {
        "Level": "3",
        "Name": "UMP"
    },
    {
        "Level": "4",
        "Name": "RC"
    },
    {
        "Level": "1",
        "Name": "1UKM"
    },
    {
        "Level": "1",
        "Name": "1UNIMAS"
    },
    {
        "Level": "5",
        "Name": "P1"
    },
    {
        "Level": "4",
        "Name": "PA"
    },
    {
        "Level": "3",
        "Name": "UTM"
    },
    {
        "Level": "4",
        "Name": "K3"
    },
    {
        "Level": "PERALIHAN",
        "Name": "A"
    },
    {
        "Level": "5",
        "Name": "K1"
    },
    {
        "Level": "PERALIHAN",
        "Name": "PER A"
    },
    {
        "Level": "3",
        "Name": "UIA"
    },
    {
        "Level": "4",
        "Name": "RC1"
    },
    {
        "Level": "5",
        "Name": "PA"
    },
    {
        "Level": "4",
        "Name": "K5"
    },
    {
        "Level": "3",
        "Name": "USM"
    },
    {
        "Level": "PERALIHAN",
        "Name": "B"
    },
    {
        "Level": "4",
        "Name": "K2"
    },
    {
        "Level": "1",
        "Name": "1UM"
    },
    {
        "Level": "1",
        "Name": "UMS"
    },
    {
        "Level": "3",
        "Name": "UPM"
    },
    {
        "Level": "3",
        "Name": "UITM"
    },
    {
        "Level": "4",
        "Name": "UPSI"
    },
    {
        "Level": "1",
        "Name": "1UMP"
    },
    {
        "Level": "4",
        "Name": "P2"
    },
    {
        "Level": "5",
        "Name": "P"
    },
    {
        "Level": "5",
        "Name": "K2"
    },
    {
        "Level": "1",
        "Name": "UNIMAS"
    },
    {
        "Level": "4",
        "Name": "SAINS"
    },
    {
        "Level": "1",
        "Name": "1UITM"
    },
    {
        "Level": "1",
        "Name": "1UPM"
    }
]